terraform_wrapper/__init__.py
terraform_wrapper/terraform.py
terraform_wrapper/tfstate.py
terraform_wrapper-0.15.3.dist-info/LICENSE.txt
terraform_wrapper-0.15.3.dist-info/METADATA
terraform_wrapper-0.15.3.dist-info/WHEEL
terraform_wrapper-0.15.3.dist-info/top_level.txt
terraform_wrapper-0.15.3.dist-info/RECORD
