Metadata-Version: 2.1
Name: terraform-wrapper
Version: 0.15.3
Summary: This is a python module provide a wrapper of terraform command line tool
Home-page: https://github.com/cranzy/python-terraform
Author: Dimitar Dimitrov
Author-email: dev.dimitar.dimitrov@gmail.com
License: MIT
Platform: any
Classifier: Development Status :: 4 - Beta
Classifier: Environment :: Console
Classifier: Intended Audience :: Developers
Classifier: License :: OSI Approved :: MIT License
Classifier: Operating System :: POSIX
Classifier: Operating System :: MacOS
Classifier: Operating System :: Unix
Classifier: Programming Language :: Python
Classifier: Programming Language :: Python :: 3
Classifier: Topic :: Software Development :: Libraries :: Python Modules
Requires-Python: >=3.6
License-File: LICENSE.txt
